DocChecker/DocCheckerNet.py
DocChecker/__init__.py
DocChecker/model.py
DocChecker/utils.py
DocChecker/tree-sitter/tree-sitter-python/examples/compound-statement-without-trailing-newline.py
DocChecker/tree-sitter/tree-sitter-python/examples/crlf-line-endings.py
DocChecker/tree-sitter/tree-sitter-python/examples/mixed-spaces-tabs.py
DocChecker/tree-sitter/tree-sitter-python/examples/multiple-newlines.py
DocChecker/tree-sitter/tree-sitter-python/examples/python2-grammar-crlf.py
DocChecker/tree-sitter/tree-sitter-python/examples/python2-grammar.py
DocChecker/tree-sitter/tree-sitter-python/examples/python3-grammar-crlf.py
DocChecker/tree-sitter/tree-sitter-python/examples/python3-grammar.py
DocChecker/tree-sitter/tree-sitter-python/examples/python3.8_grammar.py
DocChecker/tree-sitter/tree-sitter-python/examples/simple-statements-without-trailing-newline.py
DocChecker/tree-sitter/tree-sitter-python/examples/tabs.py
DocChecker/tree-sitter/tree-sitter-python/examples/trailing-whitespace.py
DocChecker/tree-sitter/tree-sitter-python/test/highlight/keywords.py
DocChecker/tree-sitter/tree-sitter-python/test/highlight/parameters.py
DocChecker/tree-sitter/tree-sitter-python/test/highlight/pattern_matching.py
docchecker-0.1.3.dist-info/METADATA
docchecker-0.1.3.dist-info/WHEEL
docchecker-0.1.3.dist-info/top_level.txt
docchecker-0.1.3.dist-info/RECORD
