Metadata-Version: 2.1
Name: docchecker
Version: 0.1.3
Summary: A tool to detect the inconsistent between code and text in your source code
Author-email: "Anh T. V. Dau" <vananh09052000@gmail.com>
Project-URL: Homepage, https://github.com/Fsoft-AIC/DocChecker
Project-URL: Bug Tracker, https://github.com/Fsoft-AIC/DocChecker/issues
Classifier: Programming Language :: Python :: 3
Classifier: License :: OSI Approved :: MIT License
Classifier: Operating System :: OS Independent
Requires-Python: >=3.7
